LICENSE
MANIFEST.in
README.md
setup.cfg
setup.py
versioneer.py
juprog/__init__.py
juprog/_version.py
juprog/progress.py
juprog.egg-info/PKG-INFO
juprog.egg-info/SOURCES.txt
juprog.egg-info/dependency_links.txt
juprog.egg-info/not-zip-safe
juprog.egg-info/top_level.txt
juprog/html/README.md
juprog/html/__init__.py
juprog/html/progress-circle.js
juprog/html/css/__init__.py
juprog/html/css/circle.css